{"sections":{"custom_liquid_UfWnRM":{"type":"custom-liquid","name":"t:sections.custom-liquid.presets.name","settings":{"custom_liquid":"{%- if product -%}\n{%- comment -%}\nBreadcrumb + Subcategory Prev/Next \u2014 POPUP 210px \u2022 thumb 50x50 sin padding vertical \u2022 gap 0 con texto \u2022 title PR=15px / PL=23px\n{%- endcomment -%}\n\n{%- assign MENU_HANDLE = 'main-menu' -%}\n{%- assign url_collection = collection -%}\n{%- assign prod_col_handles = product.collections | map: 'handle' -%}\n\n{%- assign active_collection = nil -%}\n\n{%- comment -%}Nav fallback: linklists (legacy) -> menus (OS2){%- endcomment -%}\n{%- assign nav = linklists[MENU_HANDLE] -%}\n{%- if nav == nil -%}\n  {%- assign nav = menus[MENU_HANDLE] -%}\n{%- endif -%}\n\n{%- if nav and nav.links and nav.links.size > 0 -%}\n  {%- assign deep_match = nil -%}\n  {%- assign mid_match  = nil -%}\n  {%- assign top_match  = nil -%}\n  {%- for l1 in nav.links -%}\n    {%- if l1.type == 'collection_link' and l1.object and prod_col_handles contains l1.object.handle -%}\n      {%- assign top_match = l1.object -%}\n    {%- endif -%}\n    {%- if l1.links and l1.links.size > 0 -%}\n      {%- for l2 in l1.links -%}\n        {%- if l2.type == 'collection_link' and l2.object and prod_col_handles contains l2.object.handle -%}\n          {%- assign mid_match = l2.object -%}\n        {%- endif -%}\n        {%- if l2.links and l2.links.size > 0 -%}\n          {%- for l3 in l2.links -%}\n            {%- if l3.type == 'collection_link' and l3.object and prod_col_handles contains l3.object.handle -%}\n              {%- assign deep_match = l3.object -%}{%- break -%}\n            {%- endif -%}\n          {%- endfor -%}\n        {%- endif -%}\n        {%- if deep_match -%}{%- break -%}{%- endif -%}\n      {%- endfor -%}\n    {%- endif -%}\n    {%- if deep_match -%}{%- break -%}{%- endif -%}\n  {%- endfor -%}\n  {%- assign active_collection = deep_match | default: mid_match | default: top_match -%}\n{%- endif -%}\n\n{%- if active_collection == nil -%}{%- assign active_collection = url_collection -%}{%- endif -%}\n{%- if active_collection == nil -%}{%- assign active_collection = product.collections.first -%}{%- endif -%}\n\n{%- assign first_product = nil -%}\n{%- assign last_product  = nil -%}\n{%- assign prev_product  = nil -%}\n{%- assign next_product  = nil -%}\n{%- assign prev_candidate = nil -%}\n{%- assign found_current = false -%}\n\n{%- if active_collection and active_collection.products_count > 0 -%}\n  {%- for p in active_collection.products -%}\n    {%- if forloop.first -%}{%- assign first_product = p -%}{%- endif -%}\n    {%- assign last_product = p -%}\n    {%- if p.id == product.id -%}\n      {%- assign prev_product = prev_candidate -%}\n      {%- assign found_current = true -%}\n    {%- elsif found_current and next_product == nil -%}\n      {%- assign next_product = p -%}\n      {%- assign found_current = false -%}\n    {%- endif -%}\n    {%- assign prev_candidate = p -%}\n  {%- endfor -%}\n  {%- if prev_product == nil -%}{%- assign prev_product = last_product -%}{%- endif -%}\n  {%- if next_product == nil -%}{%- assign next_product = first_product -%}{%- endif -%}\n{%- endif -%}\n\n<style>\n  .product-breadcrumbs, .breadcrumbs-share-list, .mh-bcbar { overflow: visible !important; }\n  .mh-bcbar{ display:flex; align-items:center; justify-content:space-between; gap:16px; position:relative; z-index:10; isolation:isolate; }\n  .mh-left{ min-width:0; }\n  .mh-nav{ display:flex; align-items:center; gap:12px; position:relative; z-index:20; }\n\n  /* Nav gray + hover blue */\n  .mh-nav .mh-iconbtn{ color:#9aa3ad; }\n  .mh-nav .mh-iconbtn:hover{ color:#1a73e8; }\n  .mh-nav .mh-iconbtn:focus-visible{ outline:2px solid currentColor; outline-offset:2px; }\n\n  .mh-iconbtn{\n    --size:40px; width:var(--size); height:var(--size);\n    background:transparent; border:none; border-radius:0;\n    display:inline-flex; align-items:center; justify-content:center;\n    cursor:pointer; position:relative; box-shadow:none;\n    transition: transform .08s ease, opacity .15s ease, color .15s ease;\n  }\n  .mh-iconbtn svg{ width:20px; height:20px; opacity:.95; }\n\n  /* REPLACED: Card 210px \u2014 default hidden; when open moved to body & becomes interactive */\n  .mh-preview{\n    position:absolute;\n    top:36px; right:-4px;\n    width:210px; background:#fff; border-radius:12px;\n    border:1px solid #e5e7eb; box-shadow:0 12px 30px rgba(0,0,0,.16);\n    padding:10px 0;\n    display:none; z-index:9999;\n    pointer-events:none;\n    transform: translateY(2px); opacity:0;\n    transition: transform .16s cubic-bezier(.2,.8,.2,1), opacity .16s ease;\n    overflow:hidden; will-change: transform, opacity;\n  }\n  .mh-preview.is-open{ display:block; transform:translateY(0); opacity:1; pointer-events:auto; }\n  .mh-preview.is-floating{\n    position:fixed !important;\n    top: var(--mh-top, 0px);\n    left: var(--mh-left, 0px);\n    right:auto; bottom:auto;\n    z-index:10000000;\n    pointer-events:auto;\n    transform:none; opacity:1; overflow:visible;\n  }\n\n  /* GRID: 50px thumb + 0 gap with text */\n  .mh-preview .row{\n    display:grid; grid-template-columns: 50px 1fr;\n    column-gap:0; row-gap:0; align-items:center;\n  }\n\n  /* Thumb 50x50 \u2014 no vertical padding; lateral spacing ML=18 / MR=8 */\n  .mh-preview .thumb{\n    width:50px; height:50px; border-radius:8px;\n    grid-row:1 / span 2; grid-column:1;\n    display:flex; align-items:center; justify-content:center;\n    margin:0 8px 0 18px; padding:0; background:#fff; overflow:hidden;\n  }\n  .mh-preview .thumb img{\n    width:100%; height:100%; object-fit:contain; display:block; margin:0; border:0;\n  }\n\n  /* Text padding; PR=15 and PL=23 */\n  .mh-preview .title{\n    grid-column:2; grid-row:1;\n    color:#1761A2;\n    font-size:13px; font-weight:700; line-height:1.2;\n    margin:0; padding:0 15px 0 23px;\n    display:-webkit-box; -webkit-line-clamp:2; -webkit-box-orient:vertical; overflow:hidden; text-align:left;\n  }\n  .mh-preview .sku{\n    grid-column:2; grid-row:2;\n    color:#6b7280;\n    font-size:11.5px; font-weight:600; line-height:1.1;\n    margin:0; padding:0 15px 0 23px; white-space:nowrap; opacity:.9; text-align:left;\n  }\n\n  @media (max-width:767px){\n    .mh-bcbar{ flex-direction:column; gap:10px; }\n    .mh-nav{ display:none !important; }\n    .breadcrumbs{ width:100%; }\n    .breadcrumbs__list{ display:flex; flex-wrap:wrap; gap:8px; justify-content:center; text-align:center; width:100%; }\n    .breadcrumbs__item{ display:inline-flex; }\n  }\n</style>\n\n<div class=\"page-width container-fluid\">\n  <div class=\"product-breadcrumbs mb-4\">\n    <div class=\"row\">\n      <div class=\"col-12\">\n        <div class=\"mh-bcbar\">\n          <div class=\"mh-left breadcrumbs-share-list\">\n            <nav class=\"breadcrumbs\" role=\"navigation\" aria-label=\"breadcrumbs\">\n              <ol class=\"breadcrumbs__list\">\n                <li class=\"breadcrumbs__item\">\n                  <a class=\"breadcrumbs__link link\" href=\"/\" title=\"Home\">Home</a>\n                </li>\n\n                <!-- 1) Products -> All Products -->\n                <li class=\"breadcrumbs__item\">\n                  <a class=\"breadcrumbs__link link\" href=\"/collections/all\" title=\"All Products\">All Products</a>\n                </li>\n\n                <!-- 2) Main category (top_match) BEFORE active_collection -->\n{%- assign top_is_all = false -%}\n{%- if top_match -%}\n  {%- assign top_title_down = top_match.title | downcase -%}\n  {%- if top_match.handle == 'all' or top_match.url == '/collections/all' or top_title_down == 'all products' or top_title_down == 'products' -%}\n    {%- assign top_is_all = true -%}\n  {%- endif -%}\n{%- endif -%}\n\n{%- if top_match and top_is_all == false and active_collection and top_match.handle != active_collection.handle -%}\n  <li class=\"breadcrumbs__item\">\n    <a class=\"breadcrumbs__link link\" href=\"{{ top_match.url }}\" title=\"{{ top_match.title }}\">{{- top_match.title -}}</a>\n  </li>\n{%- endif -%}\n\n\n                {%- comment -%}\n                  Optional: if deep_match exists, show mid_match in between (keeps hierarchy clean).\n                  This does NOT break your requested case; it only improves deeper trees.\n                {%- endcomment -%}\n                {%- if deep_match and mid_match and active_collection and active_collection.handle == deep_match.handle -%}\n                  {%- if top_match == nil or mid_match.handle != top_match.handle -%}\n                    <li class=\"breadcrumbs__item\">\n                      <a class=\"breadcrumbs__link link\" href=\"{{ mid_match.url }}\" title=\"{{ mid_match.title }}\">{{- mid_match.title -}}</a>\n                    </li>\n                  {%- endif -%}\n                {%- endif -%}\n\n                {% if active_collection %}\n                  <li class=\"breadcrumbs__item\">\n                    <a class=\"breadcrumbs__link link\" href=\"{{ active_collection.url }}\" title=\"{{ active_collection.title }}\">{{- active_collection.title -}}</a>\n                  </li>\n                {% endif %}\n\n                <li class=\"breadcrumbs__item\">\n                  <span class=\"breadcrumbs__link_no\" aria-current=\"page\">{{ product.title }}</span>\n                </li>\n              </ol>\n            </nav>\n          </div>\n\n          {% if active_collection and prev_product and next_product %}\n            {% assign prev_img  = prev_product.featured_image | default: nil %}\n            {% assign next_img  = next_product.featured_image | default: nil %}\n            {% assign prev_sku  = prev_product.selected_or_first_available_variant.sku | default: '' %}\n            {% assign next_sku  = next_product.selected_or_first_available_variant.sku | default: '' %}\n\n            <div class=\"mh-nav\" aria-label=\"Adjacent product navigation\">\n              <!-- Prev -->\n              <a class=\"mh-iconbtn\"\n                 href=\"{{ prev_product.url | within: active_collection }}\"\n                 aria-label=\"Previous product\"\n                 data-preview-title=\"{{ prev_product.title | escape }}\"\n                 data-preview-sku=\"{{ prev_sku | escape }}\"\n                 data-preview-img=\"{% if prev_img %}{{ prev_img | image_url: width: 220 }}{% endif %}\">\n                <svg viewBox=\"0 0 24 24\" aria-hidden=\"true\" focusable=\"false\"><path d=\"M15 6l-6 6 6 6\" fill=\"none\" stroke=\"currentColor\" stroke-width=\"2\" stroke-linecap=\"round\" stroke-linejoin=\"round\"/></svg>\n                <div class=\"mh-preview\" role=\"dialog\" aria-label=\"Previous product preview\" aria-hidden=\"true\">\n                  <div class=\"row\">\n                    <div class=\"thumb\"><img alt=\"\" src=\"\"></div>\n                    <div class=\"title\"></div>\n                    <div class=\"sku\"></div>\n                  </div>\n                </div>\n              </a>\n\n              <!-- Subcategory -->\n              <a class=\"mh-iconbtn\" href=\"{{ active_collection.url }}\" aria-label=\"Back to {{ active_collection.title | escape }}\">\n                <svg viewBox=\"0 0 24 24\" aria-hidden=\"true\" focusable=\"false\">\n                  <g fill=\"currentColor\">\n                    <circle cx=\"5\" cy=\"5\" r=\"2\"/><circle cx=\"12\" cy=\"5\" r=\"2\"/><circle cx=\"19\" cy=\"5\" r=\"2\"/>\n                    <circle cx=\"5\" cy=\"12\" r=\"2\"/><circle cx=\"12\" cy=\"12\" r=\"2\"/><circle cx=\"19\" cy=\"12\" r=\"2\"/>\n                    <circle cx=\"5\" cy=\"19\" r=\"2\"/><circle cx=\"12\" cy=\"19\" r=\"2\"/><circle cx=\"19\" cy=\"19\" r=\"2\"/>\n                  </g>\n                </svg>\n              </a>\n\n              <!-- Next -->\n              <a class=\"mh-iconbtn\"\n                 href=\"{{ next_product.url | within: active_collection }}\"\n                 aria-label=\"Next product\"\n                 data-preview-title=\"{{ next_product.title | escape }}\"\n                 data-preview-sku=\"{{ next_sku | escape }}\"\n                 data-preview-img=\"{% if next_img %}{{ next_img | image_url: width: 220 }}{% endif %}\">\n                <svg viewBox=\"0 0 24 24\" aria-hidden=\"true\" focusable=\"false\"><path d=\"M9 6l6 6-6 6\" fill=\"none\" stroke=\"currentColor\" stroke-width=\"2\" stroke-linecap=\"round\" stroke-linejoin=\"round\"/></svg>\n                <div class=\"mh-preview\" role=\"dialog\" aria-label=\"Next product preview\" aria-hidden=\"true\">\n                  <div class=\"row\">\n                    <div class=\"thumb\"><img alt=\"\" src=\"\"></div>\n                    <div class=\"title\"></div>\n                    <div class=\"sku\"></div>\n                  </div>\n                </div>\n              </a>\n            </div>\n          {% endif %}\n        </div>\n      </div>\n    </div>\n  </div>\n</div>\n\n<script>\n/* REPLACEMENT SCRIPT: move preview to body to avoid clipping; Esc-to-close; fix link navigation (no preventDefault on click) */\n(function(){\n  const clamp = (v, a, b) => Math.max(a, Math.min(v, b));\n\n  document.querySelectorAll('.mh-iconbtn').forEach(function(btn){\n    const card = btn.querySelector('.mh-preview');\n    if (!card) return;\n\n    const imgEl = card.querySelector('.thumb img');\n    const titleEl = card.querySelector('.title');\n    const skuEl = card.querySelector('.sku');\n\n    // Keep references to restore DOM position later\n    let originalParent = null;\n    let originalNext = null;\n    let isOpen = false;\n\n    function fill() {\n      const src = btn.getAttribute('data-preview-img') || '';\n      const t = btn.getAttribute('data-preview-title') || '';\n      const s = btn.getAttribute('data-preview-sku') || '';\n      if (src) imgEl.src = src;\n      titleEl.textContent = t;\n      skuEl.textContent = s ? ('SKU: ' + s) : 'SKU: \u2014';\n    }\n\n    function measureAndPlace() {\n      const r = btn.getBoundingClientRect();\n      const vw = window.innerWidth, vh = window.innerHeight;\n      const popupW = 210, GAP = 4;\n\n      // Temporarily show to measure size\n      card.style.visibility = 'hidden';\n      card.style.display = 'block';\n      const measuredH = card.offsetHeight || 96;\n      card.style.display = '';\n      card.style.visibility = '';\n\n      let top = r.bottom + GAP;\n      let left = r.right - popupW;\n\n      left = clamp(left, 8, vw - popupW - 8);\n      if (top + measuredH > vh - 8) top = r.top - measuredH - GAP;\n      top = clamp(top, 8, vh - measuredH - 8);\n\n      card.style.setProperty('--mh-top', top + 'px');\n      card.style.setProperty('--mh-left', left + 'px');\n    }\n\n    function open() {\n      if (isOpen) return;\n      fill();\n\n      // move to body so it won't be clipped by PDP or other ancestors\n      if (card.parentNode !== document.body) {\n        originalParent = card.parentNode;\n        originalNext = card.nextSibling;\n        document.body.appendChild(card);\n      }\n\n      card.style.pointerEvents = 'auto'; // allow interaction\n      card.style.zIndex = '10000000';\n      card.classList.add('is-open', 'is-floating');\n      card.setAttribute('aria-hidden', 'false');\n\n      measureAndPlace();\n      window.addEventListener('resize', measureAndPlace);\n      window.addEventListener('scroll', measureAndPlace, { passive: true });\n      window.addEventListener('keydown', onKeyDown);\n      isOpen = true;\n    }\n\n    function close() {\n      if (!isOpen) return;\n      card.classList.remove('is-open', 'is-floating');\n      card.setAttribute('aria-hidden', 'true');\n      card.style.pointerEvents = '';\n      card.style.zIndex = '';\n\n      // restore original DOM position so theme DOM remains predictable\n      if (originalParent && originalParent !== document.body) {\n        if (originalNext) originalParent.insertBefore(card, originalNext);\n        else originalParent.appendChild(card);\n        originalParent = null;\n        originalNext = null;\n      }\n\n      window.removeEventListener('resize', measureAndPlace);\n      window.removeEventListener('scroll', measureAndPlace);\n      window.removeEventListener('keydown', onKeyDown);\n      isOpen = false;\n    }\n\n    function onKeyDown(e) {\n      if (e.key === 'Escape' || e.key === 'Esc') close();\n    }\n\n    // Interactions \u2014 hover/focus\n    btn.addEventListener('mouseenter', open);\n    btn.addEventListener('mouseleave', close);\n    btn.addEventListener('focus', open, true);\n    btn.addEventListener('blur', close, true);\n\n    // allow anchor navigation \u2014 do NOT preventDefault()\n    btn.addEventListener('click', function(){});\n  });\n})();\n</script>\n{%- endif -%}","color_scheme":"","padding_top":20,"padding_bottom":0}},"main_product_knCpEk":{"type":"main-product","blocks":{"text_VREWcp":{"type":"text","settings":{"text":"<strong>{{ product.metafields.custom.brand.value }}</strong>","text_style":"body"}},"title_4WN4Hx":{"type":"title","settings":{}},"price_4iDF4i":{"type":"price","settings":{}},"sku_dbJGXK":{"type":"sku","settings":{"text_style":"body"}},"variant_picker_a8Lh7E":{"type":"variant_picker","settings":{"picker_type":"button","swatch_shape":"circle"}},"quantity_selector_3tBddz":{"type":"quantity_selector","settings":{}},"buy_buttons_ghREYE":{"type":"buy_buttons","settings":{"show_dynamic_checkout":false,"show_gift_card_recipient":false}},"custom_liquid_hWczik":{"type":"custom_liquid","name":"Spacer","settings":{"custom_liquid":"<div aria-hidden=\"true\" style=\"display:block !important;width:20px !important;height:20px !important;min-height:20px !important;margin:0 !important;padding:0 !important;line-height:0;font-size:0;clear:both !important;\">&nbsp;</div>"}},"custom_liquid_zcMTkR":{"type":"custom_liquid","settings":{"custom_liquid":"<p\n                  class=\"product__sku{% if block.settings.text_style == 'uppercase' %} caption-with-letter-spacing{% elsif block.settings.text_style == 'subtitle' %} subtitle{% endif %}{% if product.selected_or_first_available_variant.sku.size == 0 %} visibility-hidden{% endif %}\"\n                  id=\"Sku-{{ section.id }}\"\n                  role=\"status\"\n                  {{ block.shopify_attributes }}\n                >\n                  <span class=\"visually-hidden\">{{ 'products.product.sku' | t }}:</span>\n                  {{- product.selected_or_first_available_variant.sku -}}\n                </p>"}},"custom_liquid_PdpMeta":{"type":"custom_liquid","name":"Value props","settings":{"custom_liquid":"<div class=\"pdp-meta\">\n  <div class=\"pdp-meta__chips\" role=\"list\">\n    <span class=\"pdp-meta__chip\" role=\"listitem\">Crew-tested comfort<\\/span>\n    <span class=\"pdp-meta__chip\" role=\"listitem\">Compliance-ready details<\\/span>\n    <span class=\"pdp-meta__chip\" role=\"listitem\">Fast ship options<\\/span>\n  <\\/div>\n  <div class=\"pdp-meta__cards\" role=\"list\">\n    <article class=\"pdp-meta__card\" role=\"listitem\">\n      <p class=\"pdp-meta__eyebrow\">Field clarity<\\/p>\n      <h3 class=\"pdp-meta__title\">Specs surfaced without hunting<\\/h3>\n      <p class=\"pdp-meta__text\">Certification notes, SKUs, and fit guidance stay above the fold so crews can approve faster.<\\/p>\n    <\\/article>\n    <article class=\"pdp-meta__card\" role=\"listitem\">\n      <p class=\"pdp-meta__eyebrow\">Shift endurance<\\/p>\n      <h3 class=\"pdp-meta__title\">Comfort that keeps teams focused<\\/h3>\n      <p class=\"pdp-meta__text\">Breathable liners, anti-fog coatings, and adjustable fit cues are highlighted to cut buyer friction.<\\/p>\n    <\\/article>\n    <article class=\"pdp-meta__card\" role=\"listitem\">\n      <p class=\"pdp-meta__eyebrow\">Procurement ready<\\/p>\n      <h3 class=\"pdp-meta__title\">Clear CTAs for bulk or rush<\\/h3>\n      <p class=\"pdp-meta__text\">Rapid-add carts sit next to quantity controls with reassurance about lead times and support.<\\/p>\n    <\\/article>\n  <\\/div>\n<\\/div>"}},"custom_liquid_ActionBand":{"type":"custom_liquid","name":"Action band","settings":{"custom_liquid":"<div class=\"pdp-action-band\" role=\"presentation\">\n  <div class=\"pdp-action-band__item\">\n    <p class=\"pdp-action-band__eyebrow\">Lead time</p>\n    <p class=\"pdp-action-band__title\">Ships in 24-48 hrs</p>\n    <p class=\"pdp-action-band__text\">Expedited options and distributor delivery available at checkout.</p>\n  </div>\n  <div class=\"pdp-action-band__item\">\n    <p class=\"pdp-action-band__eyebrow\">Support</p>\n    <p class=\"pdp-action-band__title\">Talk to a PPE specialist</p>\n    <a class=\"pdp-action-band__pill\" href=\"/pages/contact\">Schedule a call</a>\n  </div>\n  <div class=\"pdp-action-band__item\">\n    <p class=\"pdp-action-band__eyebrow\">Compliance</p>\n    <p class=\"pdp-action-band__title\">OSHA/ANSI ready</p>\n    <p class=\"pdp-action-band__text\">Spec sheets and certifications stay one click away for fast approvals.</p>\n  </div>\n</div>"}}},"block_order":["text_VREWcp","title_4WN4Hx","price_4iDF4i","custom_liquid_ActionBand","custom_liquid_PdpMeta","sku_dbJGXK","variant_picker_a8Lh7E","quantity_selector_3tBddz","buy_buttons_ghREYE","custom_liquid_hWczik","custom_liquid_zcMTkR"],"settings":{"enable_sticky_info":true,"color_scheme":"scheme-1","media_size":"medium","constrain_to_viewport":false,"media_fit":"cover","gallery_layout":"stacked","media_position":"left","image_zoom":"lightbox","mobile_thumbnails":"show","hide_variants":true,"enable_video_looping":true,"padding_top":4,"padding_bottom":68}},"main_product_details_XmVyVJ":{"type":"main-product-details","disabled":true,"settings":{"padding_top_desktop":"80px","padding_bottom_desktop":"80px","padding_top_mobile":"40px","padding_bottom_mobile":"40px"}},"17597761342469516c":{"type":"_blocks","blocks":{"ai_gen_block_9a245ff_H4ihCA":{"type":"ai_gen_block_9a245ff","settings":{"heading":"You may also like","collection_override":"","products_limit":6,"layout":"carousel","autoplay":false,"autoplay_speed":4,"show_description":true,"show_add_to_cart":false,"desktop_image_ratio":"1","desktop_image_fit":"cover","desktop_card_min_width":150,"desktop_card_max_width":270,"desktop_card_padding":8,"desktop_card_gap":15,"tablet_image_ratio":"1","tablet_image_fit":"cover","tablet_card_min_width":170,"tablet_card_max_width":250,"tablet_card_padding":14,"tablet_card_gap":16,"mobile_image_ratio":"1","mobile_image_fit":"cover","mobile_card_min_width":140,"mobile_card_max_width":200,"mobile_card_padding":8,"mobile_card_gap":10,"heading_size":32,"heading_weight":"600","heading_color":"#222222","title_size":19,"title_weight":"600","title_color":"#222222","subtitle_size":15,"subtitle_weight":"400","subtitle_color":"#666666","price_size":17,"price_weight":"600","price_color":"#0a5ba6","mobile_title_size":14,"mobile_subtitle_size":12,"mobile_price_size":14,"card_background":"#ffffff","card_border_color":"#f3f3f3","card_border_thickness":1,"card_corner_radius":12,"button_background":"#0a5ba6","button_hover_background":"#084a8a","button_text_color":"rgba(0,0,0,0)"},"blocks":{}}},"block_order":["ai_gen_block_9a245ff_H4ihCA"],"name":"You may also like","settings":{}},"1758310866f3ce4031":{"type":"apps","blocks":{"junip_junip_product_review_gPCpTG":{"type":"shopify://apps/junip/blocks/junip-product-review/dc14f5a8-ed15-41b1-ad08-cfba23f9789b","settings":{"product":"{{product}}","title":"","alignment":""}}},"block_order":["junip_junip_product_review_gPCpTG"],"settings":{"include_margins":true}},"related-products":{"type":"related-products","disabled":true,"custom_css":[".gradient {background: transparent !important;}"],"settings":{"heading":"You may also like","heading_size":"h2","products_to_show":8,"columns_desktop":5,"color_scheme":"scheme-1","image_ratio":"square","image_shape":"default","show_secondary_image":false,"show_vendor":false,"show_rating":true,"columns_mobile":"2","padding_top":20,"padding_bottom":20}},"pdp_storytelling_hero":{"type":"pdp-storytelling","settings":{"eyebrow":"New product page look","heading":"Story-first product details your crews will actually read","subheading":"Move specs, compliance, and buying confidence into one glance-friendly layout with modular cards your team can edit without code.","cta_text":"Talk to an expert","cta_link":"/pages/contact","background":"#0c2745","card_background":"#0f3159","text_color":"#f7fbff","accent_color":"#60a5fa"},"blocks":{"feature_one":{"type":"feature","settings":{"eyebrow":"Compliance","title":"Cert-friendly storytelling","text":"Call out ANSI, OSHA, and heat-stress details in a dedicated card so safety managers sign off faster.","chip_text":"Audit ready","icon":null}},"feature_two":{"type":"feature","settings":{"eyebrow":"Comfort","title":"Show how it feels to wear","text":"Use visual feature rows to highlight ventilation, anti-fog coatings, or weight so crews trust the fit.","chip_text":"Built for long shifts","icon":null}},"feature_three":{"type":"feature","settings":{"eyebrow":"Buying","title":"CTA that adapts to bulk","text":"Sticky action row keeps add-to-cart, quantity, and lead time notes together for frictionless procurement.","chip_text":"Bulk ready","icon":null}},"feature_four":{"type":"feature","settings":{"eyebrow":"Support","title":"Real humans on standby","text":"Layer in phone, chat, and distributor CTAs alongside reviews so crews know where to get help.","chip_text":"Live support","icon":null}}},"block_order":["feature_one","feature_two","feature_three","feature_four"]}},"order":["custom_liquid_UfWnRM","main_product_knCpEk","pdp_storytelling_hero","main_product_details_XmVyVJ","17597761342469516c","1758310866f3ce4031","related-products"]}
